Metadata-Version: 2.1
Name: binlog2sql-util
Version: 1.0.4
Summary: helloworld
Home-page: https://github.com/blackmonkey121/verify
Author: binlog2sql_util
Author-email: 1138514746@qq.com
License: GPLv3
Classifier: Programming Language :: Python :: 3
Classifier: License :: OSI Approved :: GNU General Public License v3 (GPLv3)
Classifier: Operating System :: OS Independent
Requires-Python: >=3.3
